flame_auto/__init__.py
flame_auto/cvae.py
flame_auto/datat.py
flame_auto/lstm.py
flame_auto/model.py
flame_auto/trainer.py
flame_auto/utils.py
flame_autob-1.0.0.dist-info/LICENSE.txt
flame_autob-1.0.0.dist-info/METADATA
flame_autob-1.0.0.dist-info/WHEEL
flame_autob-1.0.0.dist-info/top_level.txt
flame_autob-1.0.0.dist-info/RECORD
