Metadata-Version: 2.1
Name: flame-autob
Version: 1.0.0
Summary: Anomaly detection on scientific datasets
Home-page: UNKNOWN
Author: Urmila
Author-email: urmilaraj18@gmail.com
License: MIT
Platform: UNKNOWN
Classifier: License :: OSI Approved :: MIT License
Classifier: Programming Language :: Python :: 3.6
Classifier: Programming Language :: Python :: 3.7
Classifier: Programming Language :: Python :: 3.8
License-File: LICENSE.txt
Requires-Dist: torch
Requires-Dist: numpy
Requires-Dist: matplotlib
